ppa/__init__.py
ppa/_version.py
ppa/binary_package.py
ppa/constants.py
ppa/debug.py
ppa/dict.py
ppa/io.py
ppa/job.py
ppa/lp.py
ppa/ppa.py
ppa/ppa_group.py
ppa/processes.py
ppa/repository.py
ppa/result.py
ppa/source_package.py
ppa/source_publication.py
ppa/subtest.py
ppa/suite.py
ppa/text.py
ppa/trigger.py
ppa_dev_tools-0.7.0.data/scripts/ppa
ppa_dev_tools-0.7.0.dist-info/LICENSE.GPLv2
ppa_dev_tools-0.7.0.dist-info/METADATA
ppa_dev_tools-0.7.0.dist-info/WHEEL
ppa_dev_tools-0.7.0.dist-info/top_level.txt
ppa_dev_tools-0.7.0.dist-info/RECORD
