Metadata-Version: 2.1
Name: ppa-dev-tools
Version: 0.7.0
Summary: command line client for managing PPAs in Launchpad
Author-email: Bryce Harrington <bryce@canonical.com>
License: GNU GENERAL PUBLIC LICENSE
Project-URL: Homepage, https://launchpad.net/ppa-dev-tools
Project-URL: Bug Tracker, https://bugs.launchpad.net/ppa-dev-tools
Keywords: ppa,archive,ubuntu,debian
Classifier: Development Status :: 3 - Alpha
Classifier: Intended Audience :: Information Technology
Classifier: Topic :: Software Development :: Build Tools
Classifier: Topic :: System :: Archiving :: Packaging
Classifier: Topic :: System :: Software Distribution
Classifier: Programming Language :: Python :: 3
Requires-Python: >=3
License-File: LICENSE.GPLv2
